water_tools/__init__.py
water_tools/monitors.py
water_tools/ph_control.py
RPi_water_tools-0.1.5.dist-info/LICENSE
RPi_water_tools-0.1.5.dist-info/METADATA
RPi_water_tools-0.1.5.dist-info/WHEEL
RPi_water_tools-0.1.5.dist-info/top_level.txt
RPi_water_tools-0.1.5.dist-info/RECORD
