Metadata-Version: 2.1
Name: RPi-water-tools
Version: 0.1.5
Summary: This package provides various water monitoring tools for sensor and pump integration. This package uses the RPI-Control-center gpio engine as its driver to make RPI api-ification easy
Home-page: https://github.com/moha7108/water-tools
Author: Mohamed Debbagh
Author-email: moha7108@protonmail.com
License: GNU GPLv3
Project-URL: Bug Tracker, https://github.com/moha7108/water-tools/issues
Project-URL: Github, https://github.com/moha7108/water-tools
Keywords: Raspberry Pi,Raspi,Python,GPIO,API,non-blocking,ph,temperature,DFRobot,water,monitoring
Platform: UNKNOWN
Classifier: Programming Language :: Python :: 3
Classifier: License :: OSI Approved :: GNU General Public License v3 (GPLv3)
Classifier: Operating System :: POSIX :: Linux
Classifier: Development Status :: 3 - Alpha
Requires-Python: >=3
License-File: LICENSE
Requires-Dist: logzero
Requires-Dist: DFRobot-EC-PH-ADC
Requires-Dist: RPI-control-center
